ito_master/__init__.py
ito_master/mixing_manipulator/__init__.py
ito_master/mixing_manipulator/dasp_additionals.py
ito_master/modules/__init__.py
ito_master/modules/audio_utils.py
ito_master/modules/common_audioeffects.py
ito_master/modules/common_miscellaneous.py
ito_master/modules/data_normalization.py
ito_master/modules/filter.py
ito_master/modules/front_back_end.py
ito_master/modules/fx_utils.py
ito_master/modules/loss.py
ito_master/modules/normalization_imager.py
ito_master/modules/utils_data_normalization.py
ito_master/networks/__init__.py
ito_master/networks/architectures.py
ito_master/networks/network_utils.py
ito_master-0.1.1.dist-info/licenses/LICENSE
ito_master-0.1.1.dist-info/METADATA
ito_master-0.1.1.dist-info/WHEEL
ito_master-0.1.1.dist-info/top_level.txt
ito_master-0.1.1.dist-info/RECORD
